Thin_Deployer-1.1.0.data/data/etc/thin-deployer/.deployer.yml
thindeployer/__init__.py
thindeployer/Controller/DeployerController.py
thindeployer/Controller/HealthCheckController.py
thindeployer/Controller/HelloController.py
thindeployer/Controller/__init__.py
thindeployer/Service/CommandRunner.py
thindeployer/Service/Notification.py
thindeployer/Service/__init__.py
Thin_Deployer-1.1.0.dist-info/AUTHORS
Thin_Deployer-1.1.0.dist-info/LICENSE
Thin_Deployer-1.1.0.dist-info/METADATA
Thin_Deployer-1.1.0.dist-info/WHEEL
Thin_Deployer-1.1.0.dist-info/entry_points.txt
Thin_Deployer-1.1.0.dist-info/pbr.json
Thin_Deployer-1.1.0.dist-info/top_level.txt
Thin_Deployer-1.1.0.dist-info/RECORD
