Metadata-Version: 2.1
Name: Thin-Deployer
Version: 1.1.0
Summary: Webhook handler that can be used to deploy on push for example
Home-page: https://github.com/Wolnosciowiec/thin-deployer
Author: Marek Andrzejczak
Author-email: marek_andrzejczak@riseup.net
License: LGPLv3
Platform: UNKNOWN
Classifier: Development Status :: 5 - Production/Stable
Classifier: Environment :: Web Environment
Classifier: Intended Audience :: Developers
Classifier: Intended Audience :: System Administrators
Classifier: License :: OSI Approved :: GNU General Public License v3 or later (GPLv3+)
Classifier: Natural Language :: English
Classifier: Operating System :: POSIX :: Linux
Classifier: Programming Language :: Python :: 3 :: Only
Classifier: Topic :: Utilities
Classifier: Topic :: Software Development :: Version Control
Classifier: Topic :: System :: Systems Administration
Requires-Python: >=3.6
Requires-Dist: py-healthcheck (>=1.6.1)
Requires-Dist: PyYAML (>=3.12)
Requires-Dist: tornado (>=4.5)
Requires-Dist: jsonschema (>=2.6)
Requires-Dist: requests (>=2.19)
